tackleberry/__init__.py
tackleberry/chat.py
tackleberry/context.py
tackleberry/main.py
tackleberry/model.py
tackleberry/registry.py
tackleberry/registry.yaml
tackleberry/runtime/__init__.py
tackleberry/runtime/anthropic.py
tackleberry/runtime/base.py
tackleberry/runtime/groq.py
tackleberry/runtime/ollama.py
tackleberry/runtime/openai.py
tackleberry/runtime/trf.py
tackleberry-0.1.2.dist-info/METADATA
tackleberry-0.1.2.dist-info/WHEEL
tackleberry-0.1.2.dist-info/licenses/LICENSE.txt
tackleberry-0.1.2.dist-info/RECORD
